Metadata-Version: 1.0
Name: lala3
Version: 0.1
Summary: The funniest joke in the world
Home-page: UNKNOWN
Author: must
Author-email: mustorbit@posteo.de
License: MIT
Platform: UNKNOWN
